napari_vector_graphics/__init__.py
napari_vector_graphics/_image.py
napari_vector_graphics/_labels.py
napari_vector_graphics/_line.py
napari_vector_graphics/_scaler_bar.py
napari_vector_graphics/_text.py
napari_vector_graphics/_tracks.py
napari_vector_graphics/_utils.py
napari_vector_graphics/_version.py
napari_vector_graphics/_viewer.py
napari_vector_graphics/_widget.py
napari_vector_graphics/napari.yaml
napari_vector_graphics/_tests/__init__.py
napari_vector_graphics/_tests/test_tracks.py
napari_vector_graphics/_tests/test_viewer.py
napari_vector_graphics/_tests/test_widget.py
napari_vector_graphics-0.1.0.dist-info/LICENSE
napari_vector_graphics-0.1.0.dist-info/METADATA
napari_vector_graphics-0.1.0.dist-info/WHEEL
napari_vector_graphics-0.1.0.dist-info/entry_points.txt
napari_vector_graphics-0.1.0.dist-info/top_level.txt
napari_vector_graphics-0.1.0.dist-info/RECORD
