Metadata-Version: 2.1
Name: napari-vector-graphics
Version: 0.1.0
Summary: Helper plugin to export napari viewer content as SVG
Author: Jordão Bragantini
Author-email: jordao.bragantini@czbiohub.org
License: 
Project-URL: Bug Tracker, https://github.com/JoOkuma/napari-vector-graphics/issues
Project-URL: Documentation, https://github.com/JoOkuma/napari-vector-graphics#README.md
Project-URL: Source Code, https://github.com/JoOkuma/napari-vector-graphics
Project-URL: User Support, https://github.com/JoOkuma/napari-vector-graphics/issues
Classifier: Development Status :: 2 - Pre-Alpha
Classifier: Framework :: napari
Classifier: Intended Audience :: Developers
Classifier: License :: OSI Approved :: BSD License
Classifier: Operating System :: OS Independent
Classifier: Programming Language :: Python
Classifier: Programming Language :: Python :: 3
Classifier: Programming Language :: Python :: 3 :: Only
Classifier: Programming Language :: Python :: 3.9
Classifier: Programming Language :: Python :: 3.10
Classifier: Programming Language :: Python :: 3.11
Classifier: Programming Language :: Python :: 3.12
Classifier: Topic :: Scientific/Engineering :: Image Processing
Requires-Python: >=3.9
License-File: LICENSE
Requires-Dist: numpy
Requires-Dist: drawsvg
Requires-Dist: qtpy
Requires-Dist: scikit-image
Provides-Extra: testing
Requires-Dist: tox; extra == "testing"
Requires-Dist: pytest; extra == "testing"
Requires-Dist: pytest-cov; extra == "testing"
Requires-Dist: pytest-qt; extra == "testing"
Requires-Dist: napari; extra == "testing"
Requires-Dist: pyqt5; extra == "testing"
Provides-Extra: all
Requires-Dist: opencv-python-headless; extra == "all"
